pyguetzli-1.0.17.dist-info/METADATA
pyguetzli-1.0.17.dist-info/RECORD
pyguetzli-1.0.17.dist-info/top_level.txt
pyguetzli-1.0.17.dist-info/WHEEL
pyguetzli-1.0.17.dist-info/LICENSE
pyguetzli/guetzli.py
pyguetzli/__init__.py
pyguetzli/guetzli_build.py
pyguetzli/pil_image.py
pyguetzli/_guetzli.abi3.so
