Metadata-Version: 2.1
Name: pyguetzli
Version: 1.0.17
Summary: Python bindings for Google's Guetzli, a JPEG encoder that optimises JPEG compression
Home-page: https://github.com/wanadev/pyguetzli
Author: Wanadev
Author-email: contact@wanadev.fr
Maintainer: Fabien LOISON, Alexis BREUST
License: Apache-2.0
Project-URL: Source Code, https://github.com/wanadev/pyguetzli
Project-URL: Documentation, https://wanadev.github.io/pyguetzli/
Project-URL: Changelog, https://github.com/wanadev/pyguetzli#changelog
Project-URL: Issues, https://github.com/wanadev/pyguetzli/issues
Project-URL: Chat, https://discord.gg/BmUkEdMuFp
Keywords: image jpeg optimize guetzli
License-File: LICENSE
Requires-Dist: cffi >=1.0.0
Provides-Extra: pil
Requires-Dist: pillow ; extra == 'pil'
Provides-Extra: dev
Requires-Dist: nox ; extra == 'dev'
Requires-Dist: flake8 ; extra == 'dev'
Requires-Dist: Sphinx ; extra == 'dev'
Requires-Dist: sphinx-rtd-theme ; extra == 'dev'
Requires-Dist: pytest ; extra == 'dev'
